kwak/__init__.py
kwak/w_analysis.py
kwak/w_plotting.py
kwak/w_transform.py
kwak/plotting/__init__.py
kwak/plotting/nsigmaplots.py
kwak/plotting/plottingtools.py
kwak/plotting/scalograms.py
kwak/tools/__init__.py
kwak/tools/analysistools.py
kwak/tools/exact.py
kwak/tools/nsets.py
kwak-1.1.3.dist-info/LICENCE
kwak-1.1.3.dist-info/METADATA
kwak-1.1.3.dist-info/WHEEL
kwak-1.1.3.dist-info/top_level.txt
kwak-1.1.3.dist-info/RECORD
