Metadata-Version: 2.1
Name: kwak
Version: 1.1.3
Summary: Statistical tool for wavelet analysis
Home-page: https://github.com/alexxromero/kwak_wavelets
Author: Ben G. Lillard and Alexis Romero
Author-email: alexir2@uci.edu
License: MIT
Platform: UNKNOWN
